{
  "algorithm": {
    "parameters": [
      {
        "name": "orderId",
        "type": "integer"
      }
    ],
    "statements": [],
    "typeReturn": "Order",
    "variables": []
  },
  "routing": {
    "method": "GET",
    "parameters": [
      {
        "bind": "orderId",
        "in": "Path",
        "name": "orderId",
        "remarks": "ID of pet that needs to be fetched"
      }
    ],
    "path": "/store/order/{orderId}",
    "remarks": "Find purchase order by ID",
    "responses": [
      {
        "httpStatus": "200",
        "remarks": "successful operation",
        "typeName": "Order"
      },
      {
        "httpStatus": "400",
        "remarks": "Invalid ID supplied"
      },
      {
        "httpStatus": "404",
        "remarks": "Order not found"
      }
    ],
    "tags": [
      "store"
    ]
  }
}